morningstar_ui/__init__.py
morningstar_utils/__init__.py
morningstar_utils-0.0.1.dist-info/METADATA
morningstar_utils-0.0.1.dist-info/WHEEL
morningstar_utils-0.0.1.dist-info/top_level.txt
morningstar_utils-0.0.1.dist-info/RECORD
