Metadata-Version: 2.1
Name: morningstar-utils
Version: 0.0.1
Summary: Package to interact with Morningstar Data
Home-page: https://developer.morningstar.com
Author: Morningstar
License: UNKNOWN
Platform: UNKNOWN
Classifier: Programming Language :: Python :: 3
Classifier: Operating System :: OS Independent
Requires-Python: >=3.6
